{
  "version": "7",
  "dialect": "sqlite",
  "entries": [
    {
      "idx": 0,
      "version": "6",
      "when": 1784358905905,
      "tag": "0000_loving_spirit",
      "breakpoints": true
    },
    {
      "idx": 1,
      "version": "6",
      "when": 1784371628942,
      "tag": "0001_gifted_spyke",
      "breakpoints": true
    },
    {
      "idx": 2,
      "version": "6",
      "when": 1784373119208,
      "tag": "0002_sleepy_toad_men",
      "breakpoints": true
    },
    {
      "idx": 3,
      "version": "6",
      "when": 1784376036779,
      "tag": "0003_bent_gabe_jones",
      "breakpoints": true
    },
    {
      "idx": 4,
      "version": "6",
      "when": 1784384641559,
      "tag": "0004_typical_mantis",
      "breakpoints": true
    },
    {
      "idx": 5,
      "version": "6",
      "when": 1784384660332,
      "tag": "0005_cloudy_carnage",
      "breakpoints": true
    },
    {
      "idx": 6,
      "version": "6",
      "when": 1784387206424,
      "tag": "0006_lying_black_queen",
      "breakpoints": true
    },
    {
      "idx": 7,
      "version": "6",
      "when": 1784419192980,
      "tag": "0007_dashing_pretty_boy",
      "breakpoints": true
    },
    {
      "idx": 8,
      "version": "6",
      "when": 1784420354153,
      "tag": "0008_yummy_quicksilver",
      "breakpoints": true
    },
    {
      "idx": 9,
      "version": "6",
      "when": 1784452384135,
      "tag": "0009_overjoyed_hardball",
      "breakpoints": true
    },
    {
      "idx": 10,
      "version": "6",
      "when": 1784456420272,
      "tag": "0010_long_shen",
      "breakpoints": true
    },
    {
      "idx": 11,
      "version": "6",
      "when": 1784467307319,
      "tag": "0011_chief_wind_dancer",
      "breakpoints": true
    },
    {
      "idx": 12,
      "version": "6",
      "when": 1784469016983,
      "tag": "0012_round_mulholland_black",
      "breakpoints": true
    },
    {
      "idx": 13,
      "version": "6",
      "when": 1784470464350,
      "tag": "0013_parched_leech",
      "breakpoints": true
    },
    {
      "idx": 14,
      "version": "6",
      "when": 1784471881705,
      "tag": "0014_watery_yellow_claw",
      "breakpoints": true
    }
  ]
}